pydepcall/Node.py
pydepcall/__init__.py
pydepcall/build_repo_graph.py
pydepcall/constant.py
pydepcall/extractor.py
pydepcall/travel_graph.py
pydepcall/utils/__init__.py
pydepcall/utils/parser_utils.py
pydepcall/utils/utils.py
pydepcall-0.0.2.dist-info/METADATA
pydepcall-0.0.2.dist-info/WHEEL
pydepcall-0.0.2.dist-info/top_level.txt
pydepcall-0.0.2.dist-info/RECORD
